odoo9_addon_business_requirement_deliverable_default-9.0.1.0.0.99.dev1-py2.7-nspkg.pth
odoo_addons/business_requirement_deliverable_default/__openerp__.py
odoo_addons/business_requirement_deliverable_default/__init__.py
odoo_addons/business_requirement_deliverable_default/README.rst
odoo_addons/business_requirement_deliverable_default/models/product.py
odoo_addons/business_requirement_deliverable_default/models/business_requirement.py
odoo_addons/business_requirement_deliverable_default/models/__init__.py
odoo_addons/business_requirement_deliverable_default/views/product_template_view.xml
odoo_addons/business_requirement_deliverable_default/tests/test_default_resources_from_product.py
odoo_addons/business_requirement_deliverable_default/tests/__init__.py
odoo_addons/business_requirement_deliverable_default/static/img/bus_req_default.png
odoo_addons/business_requirement_deliverable_default/static/img/bus_req_default2.png
odoo_addons/business_requirement_deliverable_default/static/description/icon.png
odoo9_addon_business_requirement_deliverable_default-9.0.1.0.0.99.dev1.dist-info/top_level.txt
odoo9_addon_business_requirement_deliverable_default-9.0.1.0.0.99.dev1.dist-info/WHEEL
odoo9_addon_business_requirement_deliverable_default-9.0.1.0.0.99.dev1.dist-info/RECORD
odoo9_addon_business_requirement_deliverable_default-9.0.1.0.0.99.dev1.dist-info/metadata.json
odoo9_addon_business_requirement_deliverable_default-9.0.1.0.0.99.dev1.dist-info/DESCRIPTION.rst
odoo9_addon_business_requirement_deliverable_default-9.0.1.0.0.99.dev1.dist-info/METADATA
odoo9_addon_business_requirement_deliverable_default-9.0.1.0.0.99.dev1.dist-info/namespace_packages.txt
