Metadata-Version: 2.0
Name: odoo9-addon-business-requirement-deliverable-default
Version: 9.0.1.0.0.99.dev1
Summary: Manage default resource lines in your
Home-page: https://www.elico-corp.com/
Author: Elico Corp, Odoo Community Association (OCA)
Author-email: support@odoo-community.org
License: AGPL-3
Platform: UNKNOWN
Requires-Dist: odoo (<9.1a,>=9.0a)
Requires-Dist: odoo9-addon-business-requirement-deliverable
Classifier: Programming Language :: Python :: 2.7
Classifier: Framework :: Odoo
Classifier: License :: OSI Approved :: GNU Affero General Public License v3
